pqdict/__init__.py
pqdict/py.typed
pqdict-1.4.1.dist-info/METADATA
pqdict-1.4.1.dist-info/WHEEL
pqdict-1.4.1.dist-info/licenses/LICENSE
pqdict-1.4.1.dist-info/RECORD
