Metadata-Version: 2.4
Name: pqdict
Version: 1.4.1
Summary: A Pythonic indexed priority queue.
Project-URL: homepage, https://github.com/nvictus/pqdict
Project-URL: documentation, https://pqdict.readthedocs.io
Project-URL: repository, https://github.com/nvictus/pqdict
Project-URL: changelog, https://github.com/nvictus/pqdict/blob/master/CHANGES
Author-email: Nezar Abdennur <nabdennur@gmail.com>
License: MIT
License-File: LICENSE
Keywords: data structures,dict,heap,priority queue,scheduler
Classifier: Development Status :: 5 - Production/Stable
Classifier: License :: OSI Approved :: MIT License
Classifier: Operating System :: OS Independent
Classifier: Programming Language :: Python
Classifier: Programming Language :: Python :: 3
Classifier: Programming Language :: Python :: 3.7
Classifier: Programming Language :: Python :: 3.8
Classifier: Programming Language :: Python :: 3.9
Classifier: Programming Language :: Python :: 3.10
Classifier: Programming Language :: Python :: 3.11
Classifier: Programming Language :: Python :: 3.12
Classifier: Programming Language :: Python :: 3.13
Classifier: Programming Language :: Python :: Implementation :: CPython
Classifier: Programming Language :: Python :: Implementation :: PyPy
Requires-Python: >=3.7
Requires-Dist: importlib-metadata; python_version < '3.8'
Provides-Extra: dev
Requires-Dist: mypy; extra == 'dev'
Requires-Dist: pytest; extra == 'dev'
Requires-Dist: ruff; extra == 'dev'
Provides-Extra: docs
Requires-Dist: sphinx; extra == 'docs'
Requires-Dist: sphinx-autobuild; extra == 'docs'
Requires-Dist: sphinx-rtd-theme; extra == 'docs'
